<?xml version="1.0" encoding="UTF-8"?>
<DOC lang="Other" n="NO032058" id="A/59/49 (VOL.I)/CORR.1" date="2005/08/15">
<text>
	<body>
	<p n="1">
	  <s n="1"> Resolutionen und Beschlüsse der neunundfünfzigsten Tagung der Generalversammlung </s>
	</p>
	<p n="2">
	  <s n="2"> Korrigendum </s>
	</p>
	<p n="3">
	  <s n="3"> Resolution 59/250 </s>
	</p>
	<p n="4">
	  <s n="4"> Seite 293, Ziffer 31 </s>
	</p>
	<p n="5">
	  <s n="5"> Der Text nach der Formulierung &quot;und erklärt erneut,&quot; ist durch folgenden Wortlaut zu ersetzen: </s>
	</p>
	<p n="6">
	  <s n="6"> dass für das Entwicklungssystem der Vereinten Nationen bei der Durchführung operativer Aktivitäten der möglichst weitgehende Rückgriff auf die nationale Durchführung und auf die verfügbaren einheimischen Fachkenntnisse und Technologien die Regel sein sollte; </s>
	</p>
	<p n="7">
	  <s n="7"> A/RES/60/59/49 (Vol. </s>
	  <s n="8"> I)/Corr.1 </s>
	</p>
	<p n="8">
	  <s n="9"> A/RES/60/59/49 (Vol. </s>
	  <s n="10"> I)/Corr.1 </s>
	</p>
	<p n="9">
	  <s n="11"> Vereinte Nationen A/59/49 (Vol. </s>
	  <s n="12"> I)/Corr.1 </s>
	</p>
	</body>
</text>
</DOC>