<?xml version="1.0" encoding="UTF-8"?>
<DOC lang="Other" n="NO031456" id="S/RES/1456(2003)" date="2003/01/20">
<text>
	<body>
	<p n="1">
	  <s n="1"> Resolution 1456 (2003) </s>
	</p>
	<p n="2">
	  <s n="2"> verabschiedet auf der 4688. Sitzung des Sicherheitsrats </s>
	</p>
	<p n="3">
	  <s n="3"> am 20. Januar 2003 </s>
	</p>
	<p n="4">
	  <s n="4"> Der Sicherheitsrat </s>
	</p>
	<p n="5">
	  <s n="5"> beschließt, die beigefügte Erklärung zur Frage der Bekämpfung des Terrorismus zu verabschieden. </s>
	</p>
	<p n="6">
	  <s n="6"> Anlage </s>
	</p>
	<p n="7">
	  <s n="7"> Der Sicherheitsrat, </s>
	</p>
	<p n="8">
	  <s n="8"> am 20. Januar 2003 auf Ebene der Außenminister zusammentretend, bekräftigt: </s>
	</p>
	<p n="9">
	  <s n="9"> - Der Terrorismus in allen seinen Formen und Ausprägungen stellt eine der schwersten Bedrohungen des Friedens und der Sicherheit dar; </s>
	</p>
	<p n="10">
	  <s n="10"> - alle Akte des Terrorismus sind kriminell und nicht zu rechtfertigen, ungeachtet ihrer Beweggründe, gleichviel wann und von wem sie begangen werden, und sind unmissverständlich zu verurteilen, insbesondere wenn sie ohne Unterschied gegen Zivilpersonen gerichtet sind oder diese verletzen; </s>
	</p>
	<p n="11">
	  <s n="11"> - es besteht eine ernste und zunehmende Gefahr, dass Terroristen Zugang zu nuklearen, chemischen, biologischen und anderen potenziell tödlichen Materialien haben und diese einsetzen; es ist daher notwendig, diese Materialien stärker zu kontrollieren; </s>
	</p>
	<p n="12">
	  <s n="12"> - in einer zunehmend globalisierten Welt ist es für Terroristen leichter geworden, hochentwickelte Technologien, Kommunikationsmittel und Ressourcen für ihre kriminellen Ziele zu missbrauchen; </s>
	</p>
	<p n="13">
	  <s n="13"> - die Maßnahmen zur Aufdeckung und Eindämmung der Ströme von Finanz- und Geldmitteln für terroristische Zwecke müssen dringend verstärkt werden; </s>
	</p>
	<p n="14">
	  <s n="14"> - Terroristen müssen außerdem daran gehindert werden, sich andere kriminelle Tätigkeiten zunutze zu machen, wie etwa die grenzüberschreitende organisierte Kriminalität, illegale Drogen und den Drogenhandel, Geldwäsche und den unerlaubten Waffenhandel; </s>
	</p>
	<p n="15">
	  <s n="15"> - da Terroristen und ihre Anhänger Instabilität und Intoleranz ausnutzen, um ihre kriminellen Handlungen zu rechtfertigen, ist der Sicherheitsrat entschlossen, dagegen vorzugehen, indem er zur friedlichen Beilegung von Streitigkeiten beiträgt und sich für die Schaffung eines Klimas der gegenseitigen Toleranz und Achtung einsetzt; </s>
	</p>
	<p n="16">
	  <s n="16"> - der Terrorismus kann im Einklang mit der Charta der Vereinten Nationen und dem Völkerrecht nur durch einen dauerhaften und umfassenden Ansatz, unter aktiver Mitwirkung und Zusammenarbeit aller Staaten und internationalen und regionalen Organisationen, sowie durch verstärkte Anstrengungen auf einzelstaatlicher Ebene besiegt werden. </s>
	</p>
	<p n="17">
	  <s n="17"> Der Sicherheitsrat fordert daher, dass die folgenden Maßnahmen getroffen werden: </s>
	</p>
	<p n="18">
	  <s n="18"> Alle Staaten müssen dringend Maßnahmen zur Verhütung und Bekämpfung jeder aktiven und passiven Unterstützung des Terrorismus ergreifen und insbesondere alle einschlägigen Resolutionen des Sicherheitsrats befolgen, namentlich die Resolutionen 1373 (2001), 1390 (2002) und 1455 (2003); </s>
	</p>
	<p n="19">
	  <s n="19"> der Sicherheitsrat fordert die Staaten auf, </s>
	</p>
	<p n="20">
	  <s n="20"> a) dringend Vertragspartei aller den Terrorismus betreffenden internationalen Übereinkommen und Protokolle zu werden, insbesondere des Internationalen Übereinkommens von 1999 zur Bekämpfung der Finanzierung des Terrorismus, und alle zu diesem Zweck ergriffenen Initiativen zu unterstützen und die Hilfe und die Beratung, die nunmehr verfügbar werden, voll in Anspruch zu nehmen; </s>
	</p>
	<p n="21">
	  <s n="21"> b) einander bei der Verhütung, Untersuchung, Verfolgung und Bestrafung terroristischer Handlungen, gleichviel wo sie sich ereignen, in größtmöglichem Maße behilflich zu sein; </s>
	</p>
	<p n="22">
	  <s n="22"> c) eng zusammenzuarbeiten, um die Sanktionen gegen Terroristen und ihre Verbündeten, insbesondere die Al-Qaida und die Taliban und ihre Verbündeten, in vollem Umfang anzuwenden, wie in den Resolutionen 1267 (1999), 1390 (2002) und 1455 (2003) festgelegt, umgehende Maßnahmen zu ergreifen, um ihnen den Zugang zu den finanziellen Ressourcen zu verwehren, die sie für ihre Taten benötigen, und mit der Überwachungsgruppe nach Resolution 1363 (2001) voll zusammenzuarbeiten; </s>
	</p>
	<p n="23">
	  <s n="23"> die Staaten müssen diejenigen, die terroristische Handlungen finanzieren, planen, unterstützen oder begehen oder die den Tätern Unterschlupf gewähren, im Einklang mit dem Völkerrecht, insbesondere dem Grundsatz &quot;entweder ausliefern oder strafrechtlich verfolgen&quot;, vor Gericht bringen; </s>
	</p>
	<p n="24">
	  <s n="24"> der Ausschuss zur Bekämpfung des Terrorismus muss verstärkte Anstrengungen zur Förderung der vollinhaltlichen Durchführung der Resolution 1373 (2001) durch die Mitgliedstaaten unternehmen, insbesondere indem er die Staatenberichte prüft, die internationale Unterstützung und Zusammenarbeit erleichtert und seine Tätigkeit auch künftig auf transparente und effektive Weise wahrnimmt, und in dieser Hinsicht </s>
	</p>
	<p n="25">
	  <s n="25"> i) betont der Rat, dass die Staaten verpflichtet sind, dem Ausschuss innerhalb der von ihm festgelegten Fristen Bericht zu erstatten, fordert die 13 Staaten, die noch keinen Erstbericht vorgelegt haben, und die 56 Staaten, die mit der Vorlage weiterer Berichte im Rückstand sind, auf, ihre Berichte bis zum 31. März vorzulegen, und ersucht den Ausschuss, regelmäßig über die erzielten Fortschritte Bericht zu erstatten; </s>
	</p>
	<p n="26">
	  <s n="26"> ii) fordert der Rat die Staaten auf, auf die Informationsersuchen, Bemerkungen und Fragen des Ausschusses rasch und umfassend zu reagieren, und weist den Ausschuss an, den Rat über die erzielten Fortschritte sowie über alle Schwierigkeiten, auf die er stößt, unterrichtet zu halten; </s>
	</p>
	<p n="27">
	  <s n="27"> iii) ersucht der Rat den Ausschuss, bei der Überwachung der Durchführung der Resolution 1373 (2001) alle internationalen geeignetsten Methoden, Normen und Vorschriften zu berücksichtigen, die für die Durchführung der Resolution von Belang sind, und betont seine Unterstützung für den von dem Ausschuss verfolgten Ansatz, mit jedem Staat einen Dialog hinsichtlich der weiteren Maßnahmen aufzubauen, die zur vollen Durchführung der Resolution 1373 (2001) erforderlich sind; </s>
	</p>
	<p n="28">
	  <s n="28"> die Staaten sollen sich gegenseitig unterstützen, um ihre Fähigkeiten zur Verhütung und Bekämpfung des Terrorismus zu verbessern; der Rat stellt fest, dass eine solche Zusammenarbeit die volle und rasche Durchführung der Resolution 1373 (2001) erleichtern wird, und bittet den Ausschuss zur Bekämpfung des Terrorismus, seine Anstrengungen zur Erleichterung der Gewährung technischer und sonstiger Hilfe zu verstärken, indem er Ziele und Prioritäten für ein globales Vorgehen festsetzt; </s>
	</p>
	<p n="29">
	  <s n="29"> die Staaten müssen sicherstellen, dass jede Maßnahme, die sie zur Bekämpfung des Terrorismus ergreifen, mit allen ihren Verpflichtungen nach dem Völkerrecht im Einklang steht, insbesondere im Bereich der internationalen Menschenrechte, des Flüchtlingsvölkerrechts und des humanitären Völkerrechts; </s>
	</p>
	<p n="30">
	  <s n="30"> die internationalen Organisationen sollen ermitteln, wie sie die Wirksamkeit ihrer Maßnahmen zur Bekämpfung des Terrorismus erhöhen können, namentlich indem sie miteinander und mit anderen maßgeblichen internationalen Akteuren einen Dialog führen und Informationen austauschen; der Rat richtet diesen Appell insbesondere an diejenigen Fachorgane und -organisationen, die sich mit der Kontrolle des Einsatzes nuklearer, chemischer, biologischer und anderer tödlicher Materialien beziehungsweise des Zugangs dazu befassen; in diesem Zusammenhang ist zu betonen, wie wichtig es ist, die bestehenden rechtlichen Verpflichtungen auf dem Gebiet der Abrüstung, der Rüstungsbegrenzung und der Nichtverbreitung in vollem Umfang einzuhalten und erforderlichenfalls die diesbezüglichen internationalen Übereinkünfte zu stärken; </s>
	</p>
	<p n="31">
	  <s n="31"> die regionalen und subregionalen Organisationen sollen mit dem Ausschuss zur Bekämpfung des Terrorismus und anderen internationalen Organisationen zusammenarbeiten, um den Austausch der geeignetsten Methoden zur Bekämpfung des Terrorismus zu erleichtern und ihren Mitgliedern bei der Erfüllung ihrer Verpflichtungen auf diesem Gebiet behilflich zu sein; </s>
	</p>
	<p n="32">
	  <s n="32"> die Teilnehmer an der für den 7. März 2003 anberaumten Sondertagung des Ausschusses zur Bekämpfung des Terrorismus mit internationalen, regionalen und subregionalen Organisationen sollen diese Gelegenheit dafür nutzen, eiligst Fortschritte in den in dieser Erklärung angesprochenen Fragen zu erzielen, die in den Tätigkeitsbereich dieser Organisationen fallen; </s>
	</p>
	<p n="33">
	  <s n="33"> außerdem </s>
	</p>
	<p n="34">
	  <s n="34"> 10. betont der Sicherheitsrat, dass nachhaltige internationale Anstrengungen zur Förderung des Dialogs und zur Erweiterung des Verständnisses zwischen den Kulturen, um unterschiedslose Angriffe auf andere Religionen und Kulturen zu verhindern, zur Verstärkung der Kampagne gegen den Terrorismus und zur Regelung ungelöster regionaler Konflikte sowie des gesamten Spektrums von Weltproblemen, einschließlich der Entwicklungsfragen, zur internationalen Kooperation und Zusammenarbeit beitragen werden, die ihrerseits notwendig sind, um den Terrorismus nachhaltig auf möglichst breiter Front zu bekämpfen; </s>
	</p>
	<p n="35">
	  <s n="35"> 11. bekräftigt der Rat seine feste Entschlossenheit, den Terrorismus im Einklang mit seiner Verantwortung nach der Charta der Vereinten Nationen mit noch stärkerem Nachdruck zu bekämpfen, nimmt Kenntnis von den Beiträgen auf seiner Sitzung am 20. Januar 2003 zur Stärkung der Rolle der Vereinten Nationen auf diesem Gebiet und bittet die Mitgliedstaaten, weitere Beiträge mit diesem Ziel zu erarbeiten; </s>
	</p>
	<p n="36">
	  <s n="36"> 12. bittet der Rat den Generalsekretär, innerhalb von 28 Tagen einen Bericht mit einer Zusammenfassung aller bei der Ratssitzung auf Ministerebene gemachten Vorschläge sowie aller von den Ratsmitgliedern dazu abgegebenen Kommentare und Stellungnahmen vorzulegen; </s>
	</p>
	<p n="37">
	  <s n="37"> 13. ermutigt der Rat die Mitgliedstaaten der Vereinten Nationen, bei der Regelung aller noch offenen Fragen zusammenzuarbeiten, mit dem Ziel, den Entwurf des umfassenden Übereinkommens über den internationalen Terrorismus und den Entwurf des internationalen Übereinkommens zur Bekämpfung von Akten des Nuklearterrorismus im Konsens zu verabschieden; </s>
	</p>
	<p n="38">
	  <s n="38"> 14. beschließt der Rat, die zur Verwirklichung dieser Erklärung ergriffenen Maßnahmen auf weiteren Sitzungen des Sicherheitsrats zu überprüfen. </s>
	</p>
	<p n="39">
	  <s n="39"> Vereinte Nationen S/RES/1456 (2003) </s>
	</p>
	<p n="40">
	  <s n="40"> Vorauskopie des Deutschen Übersetzungsdienstes, Vereinte Nationen, New York. </s>
	  <s n="41"> Der endgültige amtliche Wortlaut der Übersetzung erscheint im Offiziellen Protokoll der Generalversammlung bzw. des Sicherheitsrats. </s>
	</p>
	</body>
</text>
</DOC>